plinkio/__init__.py
plinkio/cplinkio.cpython-38-darwin.so
plinkio/plinkfile.py
tests/__init__.py
tests/write_test.py
plinkio-0.9.8.dist-info/COPYING
plinkio-0.9.8.dist-info/METADATA
plinkio-0.9.8.dist-info/WHEEL
plinkio-0.9.8.dist-info/top_level.txt
plinkio-0.9.8.dist-info/RECORD
