Metadata-Version: 2.1
Name: plinkio
Version: 0.9.8
Summary: A library for parsing plink genotype files
Home-page: https://github.com/mfranberg/libplinkio
Author: Mattias Franberg
Author-email: mattias.franberg@gmail.com
License: BSD
Keywords: plinkio bioinformatics genetics
Platform: UNKNOWN
Classifier: Development Status :: 4 - Beta
Classifier: Intended Audience :: Science/Research
Classifier: Topic :: Scientific/Engineering :: Bio-Informatics
Classifier: License :: OSI Approved :: BSD License
Classifier: Programming Language :: Python :: 2
Classifier: Programming Language :: Python :: 2.7
Classifier: Programming Language :: Python :: 3
Classifier: Programming Language :: Python :: 3.2
Classifier: Programming Language :: Python :: 3.3
Classifier: Programming Language :: Python :: 3.4
